microdb/__init__.py
microdb-0.1.3.dist-info/METADATA
microdb-0.1.3.dist-info/RECORD
microdb-0.1.3.dist-info/WHEEL
microdb-0.1.3.dist-info/top_level.txt
